road_agent/__init__.py
road_agent/router/__init__.py
road_agent-1.0.1.dist-info/LICENSE
road_agent-1.0.1.dist-info/METADATA
road_agent-1.0.1.dist-info/WHEEL
road_agent-1.0.1.dist-info/top_level.txt
road_agent-1.0.1.dist-info/RECORD
