Metadata-Version: 2.1
Name: road-agent
Version: 1.0.1
Summary: Object-oriented framework for modeling of mobile agents.
Home-page: http://gitlab.com/rgarcia-herrera/road-agent
Author: Rodrigo Garcia
Author-email: rgarcia@iecologia.unam.mx
License: GPLv3
Platform: UNKNOWN
Classifier: License :: OSI Approved :: GNU General Public License v3 (GPLv3)
Classifier: Programming Language :: Python :: 2.7
Classifier: Topic :: Scientific/Engineering :: Information Analysis
Classifier: Intended Audience :: Science/Research
Classifier: Topic :: Scientific/Engineering
Requires-Dist: LatLon
Requires-Dist: requests
Requires-Dist: sklearn
Requires-Dist: osmnx
